spatialign/__init__.py
spatialign/module/__init__.py
spatialign/module/dgi.py
spatialign/module/domain_specific_batch_norm.py
spatialign/module/embed_layer.py
spatialign/module/embed_model.py
spatialign/module/graph_vae.py
spatialign/module/losses.py
spatialign/module/residual_bottleneck.py
spatialign/spatialign/__init__.py
spatialign/spatialign/model.py
spatialign/spatialign/trainer.py
spatialign/utils/__init__.py
spatialign/utils/dataset.py
spatialign/utils/early_stopping.py
spatialign/utils/time_decorator.py
spatialign-1.0.2.dist-info/LICENCE
spatialign-1.0.2.dist-info/METADATA
spatialign-1.0.2.dist-info/WHEEL
spatialign-1.0.2.dist-info/top_level.txt
spatialign-1.0.2.dist-info/RECORD
