Metadata-Version: 2.1
Name: spatialign
Version: 1.0.2
Summary: spatiAlign: An Unsupervised Contrastive Learning Model for Data Integration of Spatially Resolved Transcriptomics
Home-page: https://github.com/zhangchao162/Spatialign.git
Author: zhangchao
Author-email: 1623804006@qq.com
License: UNKNOWN
Platform: UNKNOWN
Classifier: Programming Language :: Python :: 3
Classifier: License :: OSI Approved :: MIT License
Classifier: Operating System :: OS Independent
Requires-Python: >=3.8
